ez_setup.py
hpfeeds_logger-0.0.7.7.data/scripts/hpfeeds-logger
hpfeedslogger/__init__.py
hpfeedslogger/processors.py
hpfeedslogger/formatters/__init__.py
hpfeedslogger/formatters/arcsight.py
hpfeedslogger/formatters/json_formatter.py
hpfeedslogger/formatters/splunk.py
hpfeeds_logger-0.0.7.7.dist-info/METADATA
hpfeeds_logger-0.0.7.7.dist-info/WHEEL
hpfeeds_logger-0.0.7.7.dist-info/top_level.txt
hpfeeds_logger-0.0.7.7.dist-info/RECORD
