Metadata-Version: 2.1
Name: hpfeeds-logger
Version: 0.0.7.7
Summary: Python library to normalize and log hpfeeds honeypot messages
Home-page: https://github.com/threatstream/hpfeeds-logger
Author: Anomali, Inc.
Author-email: tech@threatstream.com
License: License :: OSI Approved :: GNU Lesser General Public License v2 or later (LGPLv2+)
Keywords: hpfeeds logger normalizer formatter honeypots
Platform: UNKNOWN
Classifier: Development Status :: 3 - Alpha
Classifier: Intended Audience :: Developers
Classifier: License :: OSI Approved :: GNU Lesser General Public License v2 or later (LGPLv2+)
Classifier: Natural Language :: English
Classifier: Operating System :: OS Independent
Classifier: Programming Language :: Python
Classifier: Programming Language :: Python :: 2
Classifier: Programming Language :: Python :: 2.6
Classifier: Programming Language :: Python :: 2.7
Classifier: Programming Language :: Python :: 2 :: Only
Classifier: Topic :: Software Development :: Libraries :: Python Modules
Requires-Dist: hpfeeds-threatstream (==1.1)
Requires-Dist: geoip2 (==2.9.0)
